default_value_for_each_call.py
setup.py
default_value_for_each_call.egg-info/PKG-INFO
default_value_for_each_call.egg-info/SOURCES.txt
default_value_for_each_call.egg-info/dependency_links.txt
default_value_for_each_call.egg-info/top_level.txt