Metadata-Version: 1.0
Name: default-value-for-each-call
Version: 0.6
Summary: compute function default value for each call
Home-page: UNKNOWN
Author: Chen Fengyuan
Author-email: jeova.sanctus.unus@gmail.com
License: BSD
Keywords: example documentation tutorial
Platform: UNKNOWN
